{"version":1,"resource":"file:///home/bot4u/.gemini/antigravity/scratch/luxe-jewellery/server/src/prisma/prisma.service.ts","entries":[{"id":"iHY5.ts","timestamp":1770040631754},{"id":"fPNx.ts","timestamp":1770043207613},{"id":"ZMPY.ts","source":"Workspace Edit","timestamp":1770043307782},{"id":"oVIU.ts","source":"Workspace Edit","timestamp":1770043343120},{"id":"lF04.ts","source":"Workspace Edit","timestamp":1770043376788},{"id":"3ioL.ts","source":"Workspace Edit","timestamp":1770043402282},{"id":"YOsg.ts","source":"Workspace Edit","timestamp":1770043458806}]}